flip/__about__.py
flip/__init__.py
flip/parser.py
flip/utils.py
flip/transformers/__init__.py
flip/transformers/element.py
flip/transformers/transformer.py
flip/transformers/data_augmentation/__init__.py
flip/transformers/data_augmentation/color.py
flip/transformers/data_augmentation/cut_out.py
flip/transformers/data_augmentation/flip.py
flip/transformers/data_augmentation/noise.py
flip/transformers/data_augmentation/random_crop.py
flip/transformers/data_augmentation/random_resize.py
flip/transformers/data_augmentation/rotate.py
flip/transformers/domain_randomization/__init__.py
flip/transformers/domain_randomization/draw.py
flip/transformers/domain_randomization/objects_random_position.py
flip/transformers/io/__init__.py
flip/transformers/io/csv.py
flip/transformers/io/json.py
flip/transformers/io/pascal_voc.py
flip/transformers/io/save_image.py
flip/transformers/io/save_mask.py
flip/transformers/labeler/__init__.py
flip/transformers/labeler/create_bounding_boxes.py
flip/transformers/labeler/create_masks.py
flip/transformers/labeler/under_development.py
flip_data-0.2.1.dist-info/LICENSE
flip_data-0.2.1.dist-info/METADATA
flip_data-0.2.1.dist-info/WHEEL
flip_data-0.2.1.dist-info/top_level.txt
flip_data-0.2.1.dist-info/RECORD
