Metadata-Version: 2.1
Name: flip-data
Version: 0.2.1
Summary: Generate thousands of new 2D images from a small batch of objects and backgrounds.
Home-page: https://github.com/LinkedAi/flip
Author: Diego Parra
Author-email: d@linkedai.co
License: GPL-3.0
Platform: UNKNOWN
Classifier: Programming Language :: Python :: 3
Classifier: Operating System :: OS Independent
Requires-Python: >=3.7
License-File: LICENSE
Requires-Dist: opencv-python (>=4.3.0)
Requires-Dist: numpy (>=1.19.1)
Requires-Dist: pyyaml (>=5.3.1)
Requires-Dist: jinja2 (>=2.11.2)
